{
  "basic_info": {
    "description_header": "Hi",
    "description": "I am a full-stack developer with a background in editorial and client services, which means I have a solid foundation of team communication, an obsession for detail, research, and a knack for inspiring cross-functional teams. I specialize in full-stack JavaScript technologies (MERN Stack - MongoDB, Express.js, React.js, Node.js) to build complete web applications with API systems with responsive user interfaces.",
    "section_name": {
      "about": "About me",
      "projects": "Projects",
      "skills": "Skills",
      "experience": "Experience"
    }
  },
  "projects": [
    {
      "title": "Aviato",
      "startDate": "2023",
      "description": "-",
      "images": [
        "images/portfolio/Aviato/p1.jpg",
        "images/portfolio/Aviato/p2.jpg"
      ],
      "url": "https://startling-flan-ce4f0b.netlify.app/",
      "technologies": [
        {
          "class": "devicon-angularjs-plain",
          "name": "Angular"
        },
        {
          "class": "devicon-typescript-plain",
          "name": "TypeScript"
        },
        {
          "class": "devicon-csharp-plain",
          "name": "C#"
        }
      ]
    },
    {
      "title": "Twitter 2.0",
      "startDate": "2022",
      "description": "Completed in a single week with a Software Engineer a full-stack web application using MongoDB, Express.js, React.js, and Node.js (MERN) and a user-empathetic interface with full-CRUD (create, read, update, and delete) capabilities through RESTful routing. Backend contains two database models (a tweets and comments schema) which serves user JSON data to the front-end.",
      "images": [
        "images/portfolio/Twitter2.0/p1.jpg",
        "images/portfolio/Twitter2.0/p2.jpg"
      ],
      "url": "https://joyful-liger-ab5a7d.netlify.app",
      "technologies": [
        {
          "class": "devicon-react-original",
          "name": "React"
        },
        {
          "class": "devicon-javascript-plain",
          "name": "JavaScript"
        }
      ]
    },
    {
      "title": "The Weather Window",
      "startDate": "2022",
      "description": "A client-rendered application that leverages third-party API and the read-only Navigator.geolocation property to deliver immediate weather forecast results for client's current and future weather. Collaborated with a Software Engineer in a one week sprint, engaged in daily-standups, worked on separate tickets, co-coding on blockers, and practicing version-control to create the wireframe, user stories and development of the application using React.js, JavaScript, JSX, and Node.js.",
      "images": [
        "images/portfolio/WeatherWindow/p1.jpg",
        "images/portfolio/WeatherWindow/p2.jpg"
      ],
      "url": "https://weather-window.netlify.app",
      "technologies": [
        {
          "class": "devicon-angularjs-plain",
          "name": "Angular"
        },
        {
          "class": "devicon-typescript-plain",
          "name": "TypeScript"
        },
        {
          "class": "devicon-csharp-plain",
          "name": "C#"
        }
      ]
    },
    {
      "title": "2048",
      "startDate": "2022",
      "description": "Personal project for study subject. I was responsible for testing photography application that optimizes images with popular algorithms used by graphic editors like Pixlr or Adobe Photoshop. I've earned A grade :)",
      "images": ["images/portfolio/2048/p1.jpg"],
      "url": "https://joyful-liger-ab5a7d.netlify.app",
      "technologies": [
        {
          "class": "devicon-react-original",
          "name": "React"
        },
        {
          "class": "devicon-javascript-plain",
          "name": "JavaScript"
        }
      ]
    },
    {
      "title": "Candy Crush Memory Match",
      "startDate": "2022",
      "description": "A browser-based game to engage users in a Candy Crush Saga inspired memory matching game.",
      "images": ["images/portfolio/CandyCrush/p1.jpg"],
      "url": "https://joyful-liger-ab5a7d.netlify.app",
      "technologies": [
        {
          "class": "devicon-react-original",
          "name": "React"
        },
        {
          "class": "devicon-javascript-plain",
          "name": "JavaScript"
        }
      ]
    }
  ],
  "experience": [
    {
      "company": "General Assembly",
      "title": "Software Engineer Fellow",
      "years": "10.2019 - present",
      "mainTech": [""],
      "technologies": [
          "JavaScript",
          "HTML5",
          "CSS3",
          "Python",
          "MongoDB",
          "Sass",
          "SQL",
          "Netlify",
          "Heroku",
          "PostgresSQL",
          "React",
          "Express",
          "Bootstrap",
          "Flask",
          "Django",
          "RESTful Routing",
          "NPM"
      ]
    },
    {
      "company": "True Food Kitchen",
      "title": "Server",
      "years": "03.2022 - 10.2022",
      "mainTech": [""],
      "technologies": ["Communication", "Fast-Paced", "Initiative"]
    },
    {
      "company": "Crate & Barrel",
      "title": "Sales Associate",
      "years": "07.2018 - 03.2022",
      "mainTech": [""],
      "technologies": [
        "Communication"
      ]
    },
    {
      "company": "William Reed Business Media",
      "title": "Editorial Intern",
      "years": "05.2021 - 08.2021",
      "mainTech": [""],
      "technologies": [
        "Communication"
      ]
    },
    {
      "company": "Flower Bomb Media",
      "title": "Editorial Intern",
      "years": "12.2020 - 05.2021",
      "mainTech": [""],
      "technologies": [
        "Communication"
      ]
    }
  ]
}
